pycoverm-0.6.2.dist-info/METADATA
pycoverm-0.6.2.dist-info/WHEEL
pycoverm-0.6.2.dist-info/licenses/LICENSE
pycoverm/__init__.py
pycoverm/pycoverm.pypy310-pp73-x86_64-linux-gnu.so
pycoverm-0.6.2.dist-info/RECORD
