Metadata-Version: 2.4
Name: pycoverm
Version: 0.6.2
Classifier: Intended Audience :: Science/Research
Classifier: Programming Language :: Rust
Classifier: Topic :: Scientific/Engineering :: Bio-Informatics
Classifier: Topic :: Scientific/Engineering :: Medical Science Apps.
Requires-Dist: numpy >=1.16, <3
License-File: LICENSE
Summary: Simple Python interface to CoverM's fast coverage estimation functions
Keywords: bioinformatics
Home-Page: https://github.com/apcamargo/pycoverm
Author: Antonio Camargo <antoniop.camargo@gmail.com>
Author-email: Antonio Camargo <antoniop.camargo@gmail.com>
Requires-Python: >=3.8
